README.md
setup.cfg
setup.py
two_distributions/Binomialdistribution.py
two_distributions/Gaussiandistribution.py
two_distributions/Generaldistribution.py
two_distributions/__init__.py
two_distributions.egg-info/PKG-INFO
two_distributions.egg-info/SOURCES.txt
two_distributions.egg-info/dependency_links.txt
two_distributions.egg-info/not-zip-safe
two_distributions.egg-info/top_level.txt